logomaker/__init__.py
logomaker/examples/19.05.14_colorblind.ipynb
logomaker/examples/demo_colorschemes.py
logomaker/examples/demo_fig1b.py
logomaker/examples/demo_fig1c.py
logomaker/examples/demo_fig1d.py
logomaker/examples/demo_fig1e.py
logomaker/examples/demo_fig1f.py
logomaker/examples/demo_logo.py
logomaker/examples/examples.ipynb
logomaker/examples/figure.ipynb
logomaker/examples/logos_from_datafiles.ipynb
logomaker/examples/scratch.ipynb
logomaker/examples/datafiles/ars_sequences.txt.gz
logomaker/examples/datafiles/ars_wt_sequence.txt
logomaker/examples/datafiles/crp_sites.fa
logomaker/examples/datafiles/nn_saliency_values.txt
logomaker/examples/datafiles/ss_sequences.txt
logomaker/examples/datafiles/ww_sequences.fa
logomaker/examples/logos/ars_enrichment_logo.png
logomaker/examples/logos/color_schemes.png
logomaker/examples/logos/crp_energy_logo.png
logomaker/examples/logos/figure1_logos.pdf
logomaker/examples/logos/logomaker_logo.png
logomaker/examples/logos/nn_saliency_logo.png
logomaker/examples/logos/ss_probability_logo.png
logomaker/examples/logos/ww_information_logo.png
logomaker/examples/matrices/ars_enrichment_matrix.txt
logomaker/examples/matrices/crp_counts_matrix.txt
logomaker/examples/matrices/crp_energy_matrix.txt
logomaker/examples/matrices/logomaker_logo_matrix.txt
logomaker/examples/matrices/nn_saliency_matrix.txt
logomaker/examples/matrices/ss_probability_matrix.txt
logomaker/examples/matrices/ww_counts_matrix.txt
logomaker/examples/matrices/ww_information_matrix.txt
logomaker/src/Glyph.py
logomaker/src/Logo.py
logomaker/src/__init__.py
logomaker/src/colors.py
logomaker/src/error_handling.py
logomaker/src/examples.py
logomaker/src/matrix.py
logomaker/src/validate.py
logomaker/src/__pycache__/Glyph.cpython-310.pyc
logomaker/src/__pycache__/Logo.cpython-310.pyc
logomaker/src/__pycache__/__init__.cpython-310.pyc
logomaker/src/__pycache__/colors.cpython-310.pyc
logomaker/src/__pycache__/error_handling.cpython-310.pyc
logomaker_kinase-0.8.3.dist-info/LICENSE
logomaker_kinase-0.8.3.dist-info/METADATA
logomaker_kinase-0.8.3.dist-info/WHEEL
logomaker_kinase-0.8.3.dist-info/top_level.txt
logomaker_kinase-0.8.3.dist-info/RECORD
